[
  {
    "name": "_ga_PMP5M3Y6RX",
    "value": "GS2.1.s1762711549$o1$g1$t1762711838$j53$l0$h1881936455",
    "domain": ".watchnian.com",
    "path": "/",
    "expires": 1797271838.620263,
    "size": 68,
    "httpOnly": false,
    "secure": false,
    "session": false,
    "priority": "Medium",
    "sameParty": false,
    "sourceScheme": "Secure"
  },
  {
    "name": "_ga",
    "value": "GA1.1.432227225.1762711550",
    "domain": ".watchnian.com",
    "path": "/",
    "expires": 1797271838.207632,
    "size": 29,
    "httpOnly": false,
    "secure": false,
    "session": false,
    "priority": "Medium",
    "sameParty": false,
    "sourceScheme": "Secure"
  },
  {
    "name": "--CartRecovery のトラッキングIDを設定してください---uid",
    "value": "88e21921-e4e2-47e6-a9fc-5614fda9252b",
    "domain": ".watchnian.com",
    "path": "/",
    "expires": 1793815832,
    "size": 107,
    "httpOnly": false,
    "secure": false,
    "session": false,
    "priority": "Medium",
    "sameParty": false,
    "sourceScheme": "Secure"
  },
  {
    "name": "_clck",
    "value": "ygy13a%5E2%5Eg0v%5E0%5E2139",
    "domain": ".watchnian.com",
    "path": "/",
    "expires": 1794247553,
    "size": 32,
    "httpOnly": false,
    "secure": false,
    "session": false,
    "priority": "Medium",
    "sameParty": false,
    "sourceScheme": "Secure"
  },
  {
    "name": "ippuukishi_browser",
    "value": "S",
    "domain": "watchnian.com",
    "path": "/shop",
    "expires": 1762797942.286028,
    "size": 19,
    "httpOnly": true,
    "secure": true,
    "session": false,
    "sameSite": "None",
    "priority": "Medium",
    "sameParty": false,
    "sourceScheme": "Secure"
  },
  {
    "name": "__sna_s1d",
    "value": "yP6kBV8HIeUiV2yQnicHnYu63UmwpF",
    "domain": "watchnian.com",
    "path": "/",
    "expires": 1797271547.080554,
    "size": 39,
    "httpOnly": false,
    "secure": false,
    "session": false,
    "priority": "Medium",
    "sameParty": false,
    "sourceScheme": "Secure"
  },
  {
    "name": "_ebtd",
    "value": "1.2cbnspz3ou9.1762711551",
    "domain": ".watchnian.com",
    "path": "/",
    "expires": 1797271832.316649,
    "size": 29,
    "httpOnly": false,
    "secure": false,
    "session": false,
    "priority": "Medium",
    "sameParty": false,
    "sourceScheme": "Secure"
  },
  {
    "name": "ippuukishi_agent",
    "value": "HFLd1PK45XtHFwEyY2OO8xc5eOHDltqBEWspO5CtgF3DE9hBNEXedkTHtV6BNsq6",
    "domain": "watchnian.com",
    "path": "/shop",
    "expires": 1797271545.286062,
    "size": 80,
    "httpOnly": true,
    "secure": true,
    "session": false,
    "sameSite": "None",
    "priority": "Medium",
    "sameParty": false,
    "sourceScheme": "Secure"
  },
  {
    "name": "_gcl_au",
    "value": "1.1.233685122.1762711550",
    "domain": ".watchnian.com",
    "path": "/",
    "expires": 1770487550,
    "size": 31,
    "httpOnly": false,
    "secure": false,
    "session": false,
    "priority": "Medium",
    "sameParty": false,
    "sourceScheme": "Secure"
  },
  {
    "name": "ippuukishi_secure",
    "value": "SecureKey=",
    "domain": "watchnian.com",
    "path": "/shop",
    "expires": -1,
    "size": 27,
    "httpOnly": true,
    "secure": true,
    "session": true,
    "sameSite": "None",
    "priority": "Medium",
    "sameParty": false,
    "sourceScheme": "Secure"
  },
  {
    "name": "ASP.NET_SessionId",
    "value": "0ebae40hwgtuic5jfydulr53",
    "domain": "watchnian.com",
    "path": "/",
    "expires": -1,
    "size": 41,
    "httpOnly": true,
    "secure": true,
    "session": true,
    "sameSite": "None",
    "priority": "Medium",
    "sameParty": false,
    "sourceScheme": "Secure"
  },
  {
    "name": "ippuukishi",
    "value": "Session=69380608&Key=75b98de57540ab49f212f26633ef15d3d3cdf88a9d15d9638ebb264ac79c0ec0",
    "domain": "watchnian.com",
    "path": "/shop",
    "expires": -1,
    "size": 95,
    "httpOnly": true,
    "secure": true,
    "session": true,
    "sameSite": "None",
    "priority": "Medium",
    "sameParty": false,
    "sourceScheme": "Secure"
  },
  {
    "name": "lang",
    "value": "ja",
    "domain": "watchnian.com",
    "path": "/shop",
    "expires": -1,
    "size": 6,
    "httpOnly": false,
    "secure": false,
    "session": true,
    "priority": "Medium",
    "sameParty": false,
    "sourceScheme": "Secure"
  },
  {
    "name": "_gid",
    "value": "GA1.2.182611084.1762711550",
    "domain": ".watchnian.com",
    "path": "/",
    "expires": 1762798232,
    "size": 30,
    "httpOnly": false,
    "secure": false,
    "session": false,
    "priority": "Medium",
    "sameParty": false,
    "sourceScheme": "Secure"
  }
]